{
  "source_name": "world_bank",
  "source_record_id": "OP00454481",
  "source_url": "https://projects.worldbank.org/en/projects-operations/procurement-detail/OP00454481",
  "retrieved_at": "2026-07-10T18:58:39.835062+00:00",
  "data": {
    "id": "OP00454481",
    "notice_type": "Request for Expression of Interest",
    "noticedate": "08-Jul-2026",
    "notice_lang_name": "French",
    "notice_status": "Published",
    "submission_deadline_date": "2026-07-28T00:00:00Z",
    "submission_deadline_time": "00:00",
    "project_ctry_name": "Madagascar",
    "project_id": "P174684",
    "project_name": "Economic Transformation for Inclusive Growth Project",
    "bid_reference_no": "C-514-PIC3-TOU",
    "bid_description": "Gestion et déploiement du Programme Miatrika  \r\n - Loit 1: Région DIANA\r\n - Lot 2 : Région Anosy\r\n - Lot 3 : Région Atsimo Andrefana\r\n - Lot 4 : Ste Marie",
    "procurement_group": "CS",
    "procurement_method_code": "QCBS",
    "procurement_method_name": "Quality And Cost-Based Selection",
    "contact_address": "Maison de la Réunion, 2è étage\nIsoraka\nAntananarivo",
    "contact_ctry_name": "Madagascar",
    "contact_email": "procurement@pic.mg",
    "contact_name": "Marco Razakamahefa",
    "contact_organization": "Economic Transformation for Inclusive Growth",
    "contact_phone_no": "0202236777",
    "contact_web_url": "www.pic.mg",
    "submission_date": "2026-07-08T00:00:00Z",
    "notice_text": "<p><strong>SOLLICITATION DE MANIFESTATIONS D&rsquo;INTERET</strong></p><p><strong>GESTION ET DEPLOIEMENT DU PROGRAMME MIATRIKA DANS LES ZONES D&rsquo;INTERVENTION DU PROJET PIC REPARTIS EN 4 LOTS : </strong></p><p><strong>LOT 1 &ndash; DIANA ; LOT 2 &ndash; ATSIMO ANDREFANA ; LOT 3 &ndash; ANOSY ; LOT 4 &ndash; SAINTE MARIE </strong></p><p>&nbsp;</p><p><em>Cr&eacute;dit IDA 78730</em></p><p><em>AMI N&deg; C-514-PIC3-2026</em></p><p><em>Date de lancement&nbsp;: 15 Juillet 2026</em></p><ol><li>Le Gouvernement de la R&eacute;publique de Madagascar a obtenu un financement de la Banque Mondiale pour couvrir le co&ucirc;t du Projet de Transformation &eacute;conomique pour la croissance inclusive (PIC3), et a l&rsquo;intention d&rsquo;affecter une partie du produit &agrave; des services de consultant.</li><li>Les services de consultant (&laquo; les Services &raquo;) comprennent l&rsquo;am&eacute;lioration de la comp&eacute;titivit&eacute; de l&rsquo;offre en produits et services touristiques &agrave; la destination Madagascar dans l&rsquo;ensemble et dans les zones d&rsquo;intervention du Projet PIC en particulier. L&rsquo;objectif sp&eacute;cifique est d&rsquo;assurer le pilotage, l&rsquo;organisation, la mise en &oelig;uvre, le suivi et l&rsquo;&eacute;valuation des aspects administratifs, techniques et financiers du Programme MIATRIKA dans le lot concern&eacute;, selon une logique de redevabilit&eacute; ax&eacute;e sur les r&eacute;sultats.</li><li>Les termes de r&eacute;f&eacute;rence (TDR) pour l&rsquo;&eacute;tape de proc&eacute;dure primaire d&rsquo;acquisition pour la mission sont disponibles sur le site internet www.pic.mg</li><li>La Coordination Nationale du Projet PIC3 invite d&egrave;s &agrave; pr&eacute;sent les firmes de consultants admissibles (&laquo;&nbsp;Consultant&nbsp;&raquo;) &agrave; faire part de leur int&eacute;r&ecirc;t &agrave; fournir les Services. Les Consultants int&eacute;ress&eacute;s doivent fournir des informations d&eacute;montrant qu&rsquo;ils poss&egrave;dent les qualifications requises et l&rsquo;exp&eacute;rience pertinente pour ex&eacute;cuter les Services, et joindre dans leurs dossiers au moins les documents suivants&nbsp;:</li></ol><ul><li>Une lettre de manifestation d&rsquo;int&eacute;r&ecirc;t&nbsp;en pr&eacute;cisant le lot(s) concern&eacute;(s) ;</li><li>Un dossier de pr&eacute;sentation d&eacute;taill&eacute; du cabinet (format libre), dans lequel leurs exp&eacute;riences g&eacute;n&eacute;rales et sp&eacute;cifiques, li&eacute;es &agrave; la mission, soient mise en exergue.</li></ul><p>Les crit&egrave;res de s&eacute;lection d&rsquo;une liste restreinte sont les suivants :</p><ul><li>&Ecirc;tre une entit&eacute; juridique l&eacute;galement constitu&eacute;e et &eacute;tablie dans la r&eacute;gion d&rsquo;intervention, ou un consortium avec partenaire local formel&nbsp;;</li><li>&Ecirc;tre habilit&eacute; &agrave; d&eacute;livrer des certificats de formation, ou justifier d&rsquo;un partenariat formel valide avec une entit&eacute; accr&eacute;dit&eacute;e&nbsp;;</li><li>&OElig;uvrant depuis au moins cinq (05) ans dans le domaine de renforcement de capacit&eacute; dont trois (03) ans dans la mise en &oelig;uvre de programmes de formation incluant des modules courts et des formations certifiantes&nbsp;;</li><li>D&eacute;montrer une exp&eacute;rience av&eacute;r&eacute;e dans le secteur THR et/ou du guidage touristique ;</li><li>D&eacute;montrer une capacit&eacute; &agrave; recruter, mobiliser et g&eacute;rer des formateurs qualifi&eacute;s pour la mise en &oelig;uvre des modules de formation ;</li><li>Disposer de m&eacute;canismes de gestion financi&egrave;re et de contr&ocirc;le, avec preuves de gestion de fonds de formation et/ou de projets financ&eacute;s par des partenaires techniques et financiers internationaux ;</li><li>Pr&eacute;senter des capacit&eacute;s op&eacute;rationnelles et territoriales pour la coordination locale, la mise en &oelig;uvre et le suivi des formations, y compris la gestion d&rsquo;outils num&eacute;riques d&eacute;di&eacute;s&nbsp;;</li></ul><p>La connaissance du contexte touristique local serait un atout.</p><p>Les experts cl&eacute;s ne seront pas &eacute;valu&eacute;s &agrave; l&rsquo;&eacute;tape de la pr&eacute;paration de la liste restreinte. Aussi, le dossier de manifestation d&#39;int&eacute;r&ecirc;t ne doit en aucun cas contenir d&#39;informations concernant les membres du personnel cl&eacute; mentionn&eacute;s dans les termes de r&eacute;f&eacute;rence.</p><p>5. La liste restreinte comprendra cinq (05) &agrave; huit (08) firmes ou consortium.</p><p>6. L&#39;attention des Consultants int&eacute;ress&eacute;s est attir&eacute;e sur la Section III, paragraphes, 3.15 et 3.16 du &laquo; R&egrave;glement de Passation des March&eacute;s pour les Emprunteurs de FPI &raquo; de la Banque mondiale, sixi&egrave;me &eacute;dition &ndash; F&eacute;vrier 2025, qui &eacute;nonce la politique de la Banque mondiale en mati&egrave;re de conflits d&rsquo;int&eacute;r&ecirc;ts.</p><p>7. Les Consultants peuvent s&rsquo;associer &agrave; d&rsquo;autres firmes pour am&eacute;liorer leurs qualifications, mais ils doivent indiquer clairement si l&rsquo;association prend la forme d&rsquo;un groupement et/ou d&rsquo;une sous-traitance. Dans le cas d&rsquo;un groupement, tous les membres du groupement d&rsquo;entreprises seront solidairement responsables de l&rsquo;ensemble du contrat, s&rsquo;ils sont s&eacute;lectionn&eacute;s.</p><p>8. Un Consultant sera s&eacute;lectionn&eacute; en accord avec les proc&eacute;dures de la Banque Mondiale d&eacute;finies dans le &laquo;&nbsp;R&egrave;glement de Passation de March&eacute;s pour les Emprunteurs sollicitant le Financement de Projet d&rsquo;Investissement (FPI) pour les Fournitures, Travaux, Services autres que les Services de Consultants&nbsp;&raquo;, sixi&egrave;me &eacute;dition, f&eacute;vrier 2025, suivant la m&eacute;thode de S&eacute;lection Fond&eacute;e sur la Qualit&eacute; et le Co&ucirc;t (SFQC).</p><p>9. Des informations suppl&eacute;mentaires peuvent &ecirc;tre obtenues &agrave; l&rsquo;adresse ci-dessous pendant les heures de bureau, de 09h00 &agrave; 17h00, heure locale.</p><p>10. Les manifestations d&rsquo;int&eacute;r&ecirc;t doivent &ecirc;tre fournies par &eacute;crit <u>exclusivement par mail</u> sous format PDF au plus tard le <strong><u>28 juillet 2026</u></strong> &agrave; minuit (heure locale) &agrave; l&rsquo;adresse&nbsp;: <strong>procurement@pic.mg</strong><strong> </strong></p><p>L&rsquo;objet du mail d&rsquo;envoi doit porter obligatoirement la mention suivante &laquo;&nbsp;<strong>AMI <em>N&deg; C-514-PIC3-2026</em></strong><em> </em>&ndash;<strong>GESTION ET DEPLOIEMENT DU PROGRAMME MIATRIKA en pr&eacute;cisant le(s) lot(s) concern&eacute;s</strong>.</p><p>&nbsp;</p><p>Le Projet d&eacute;cline la responsabilit&eacute; de la nonconsid&eacute;ration des dossiers de manifestations d&rsquo;int&eacute;r&ecirc;t ne respectant pas cette disposition obligatoire.</p><p>&nbsp;</p><p>Antananarivo le 15 juillet 2026</p><p>Le Projet P&ocirc;les Int&eacute;gr&eacute;s de Croissance</p>"
  }
}
